MANIFEST.in
README.rst
setup.py
pydial/__init__.py
pydial/builder.py
pydial/checker.py
pydial/double.py
pydial/enrich.py
pydial/exceptions.py
pydial/importer.py
pydial/marc.py
pydial/model.py
pydial/server.py
pydial/statistics.py
pydial/updater.py
pydial.egg-info/PKG-INFO
pydial.egg-info/SOURCES.txt
pydial.egg-info/dependency_links.txt
pydial.egg-info/requires.txt
pydial.egg-info/top_level.txt
pydial/conf/mapping.json
pydial/conf/services.json
pydial/rules/FWB_OA_rules.json
pydial/rules/article_rules.json
pydial/rules/basic_rules.json
pydial/rules/book_rules.json
pydial/rules/bookchapter_rules.json
pydial/rules/subtypes_rules.json
pydial/schemas/article-schema-v0.0.1.json
pydial/schemas/author-schema-v0.0.1.json
pydial/schemas/basics-schema-v0.0.1.json
pydial/schemas/book-schema-v0.0.1.json
pydial/schemas/book_chapter-schema-v0.0.1.json
pydial/schemas/conference_speech-schema-v0.0.1.json
pydial/schemas/doi-schema-v0.0.1.json
pydial/schemas/host_document-schema-v0.0.1.json
pydial/schemas/journal_issue-schema-v0.0.1.json
pydial/schemas/language-code.json
pydial/schemas/publication_status-schema-v0.0.1.json
pydial/schemas/publishers-schema-v0.0.1.json
pydial/schemas/report-schema-v1.0.json
pydial/schemas/series-schema-v0.0.1.json
pydial/schemas/workingpaper-schema-v1.0.json
pydial/templates/statistics/basic_stat.tpl.json
pydial/templates/statistics/detail_aggs.tpl.json
pydial/templates/statistics/localization_aggs.tpl.json
pydial/templates/statistics/timestamp_filter.tpl.json