Metadata-Version: 1.0
Name: pydial
Version: 0.3.0.3
Summary: Use DIAL Object with Python
Home-page: https://gitlab.sisg.ucl.ac.be/bibsys/pydial
Author: michotter
Author-email: renaud.michotte@uclouvain.be
License: https://opensource.org/licenses/MIT
Platform: UNKNOWN
